Metadata-Version: 2.1
Name: taxonomy-ranks
Version: 0.0.2
Summary: To get taxonomy ranks information with ETE3 from NCBI Taxonomy database.
Home-page: http://mengguanliang.com
Author: Guanliang MENG
Author-email: mengguanliang@genomics.cn
License: UNKNOWN
Platform: UNKNOWN
Classifier: Development Status :: 3 - Alpha
Classifier: Intended Audience :: Science/Research
Classifier: Topic :: Scientific/Engineering :: Bio-Informatics
Classifier: License :: OSI Approved :: GNU General Public License v3 or later (GPLv3+)
Classifier: Programming Language :: Python :: 3
Classifier: Operating System :: MacOS :: MacOS X
Classifier: Operating System :: Microsoft :: Windows
Classifier: Operating System :: POSIX :: Linux
Requires-Python: >=3
